skysurvey_skyfield/__init__.py
skysurvey_skyfield/random.py
skysurvey_skyfield/utils.py
skysurvey_skyfield-0.1.2.dist-info/LICENSE
skysurvey_skyfield-0.1.2.dist-info/METADATA
skysurvey_skyfield-0.1.2.dist-info/WHEEL
skysurvey_skyfield-0.1.2.dist-info/top_level.txt
skysurvey_skyfield-0.1.2.dist-info/RECORD
